tests/__init__.py
tests/test_topsis.py
topsis/__init__.py
topsis/topsis.py
102203166_topsis_stuti-0.1.1.dist-info/METADATA
102203166_topsis_stuti-0.1.1.dist-info/WHEEL
102203166_topsis_stuti-0.1.1.dist-info/top_level.txt
102203166_topsis_stuti-0.1.1.dist-info/RECORD
