Metadata-Version: 2.1
Name: 102203166-topsis-stuti
Version: 0.1.1
Summary: A Python package to implement the TOPSIS method for multi-criteria decision analysis.
Home-page: https://github.com/stuti-go/topsis-package
Author: Stuti Goyal
Author-email: gstu180@gmail.com
Classifier: Programming Language :: Python :: 3
Classifier: Operating System :: OS Independent
Requires-Python: >=3.6
Requires-Dist: numpy
